copp/__init__.py
copp-0.0.0.dist-info/LICENSE
copp-0.0.0.dist-info/METADATA
copp-0.0.0.dist-info/WHEEL
copp-0.0.0.dist-info/top_level.txt
copp-0.0.0.dist-info/RECORD
